{
  "pluginId": "default",
  "version": "current",
  "label": "Next",
  "banner": null,
  "badge": false,
  "noIndex": false,
  "className": "docs-version-current",
  "isLast": true,
  "docsSidebars": {
    "tutorialSidebar": [
      {
        "type": "link",
        "label": "intro",
        "href": "/esxscripts/intro",
        "docId": "intro"
      },
      {
        "type": "category",
        "label": "[esx][paid] barber shop",
        "collapsible": true,
        "collapsed": true,
        "items": [
          {
            "type": "link",
            "label": "installation",
            "href": "/esxscripts/barber_shop/esx_barber_shop",
            "docId": "barber_shop/installation"
          }
        ],
        "href": "/esxscripts/category/esxpaid-barber-shop"
      },
      {
        "type": "category",
        "label": "[esx][paid] car remote",
        "collapsible": true,
        "collapsed": true,
        "items": [
          {
            "type": "link",
            "label": "installation",
            "href": "/esxscripts/car_remote/esx_car_remote",
            "docId": "car_remote/installation"
          }
        ],
        "href": "/esxscripts/category/esxpaid-car-remote"
      },
      {
        "type": "category",
        "label": "[esx][paid] cloak room",
        "collapsible": true,
        "collapsed": true,
        "items": [
          {
            "type": "link",
            "label": "installation",
            "href": "/esxscripts/cloak_room/esx_cloakroom",
            "docId": "cloak_room/installation"
          }
        ],
        "href": "/esxscripts/category/esxpaid-cloak-room"
      },
      {
        "type": "category",
        "label": "[esx][paid] flight job",
        "collapsible": true,
        "collapsed": true,
        "items": [
          {
            "type": "link",
            "label": "installation",
            "href": "/esxscripts/flight_job/esx_flight_job",
            "docId": "flight_job/installation"
          }
        ],
        "href": "/esxscripts/category/esxpaid-flight-job"
      },
      {
        "type": "category",
        "label": "[esx][paid] pilot job",
        "collapsible": true,
        "collapsed": true,
        "items": [
          {
            "type": "link",
            "label": "installation",
            "href": "/esxscripts/pilot_job/esx_pilot_job",
            "docId": "pilot_job/installation"
          }
        ],
        "href": "/esxscripts/category/esxpaid-pilot-job"
      }
    ]
  },
  "docs": {
    "barber_shop/installation": {
      "id": "barber_shop/installation",
      "title": "installation",
      "description": "barber shop",
      "sidebar": "tutorialSidebar"
    },
    "car_remote/installation": {
      "id": "car_remote/installation",
      "title": "installation",
      "description": "car remote system",
      "sidebar": "tutorialSidebar"
    },
    "cloak_room/installation": {
      "id": "cloak_room/installation",
      "title": "installation",
      "description": "cloak room",
      "sidebar": "tutorialSidebar"
    },
    "flight_job/installation": {
      "id": "flight_job/installation",
      "title": "installation",
      "description": "flight job",
      "sidebar": "tutorialSidebar"
    },
    "intro": {
      "id": "intro",
      "title": "intro",
      "description": "welcome to esx scripts",
      "sidebar": "tutorialSidebar"
    },
    "pilot_job/installation": {
      "id": "pilot_job/installation",
      "title": "installation",
      "description": "pilot job",
      "sidebar": "tutorialSidebar"
    }
  }
}